avista_digital_exchange_sdk/DxTypes.py
avista_digital_exchange_sdk/__init__.py
avista_digital_exchange_sdk/avista_digital_exchange.py
avista_digital_exchange_sdk/client.py
avista_digital_exchange_sdk/collaborativeUtil.py
avista_digital_exchange_sdk/dataCaptureUtil.py
avista_digital_exchange_sdk/dataStoreUtil.py
avista_digital_exchange_sdk/endpointUtil.py
avista_digital_exchange_sdk/exceptions.py
avista_digital_exchange_sdk/globals.py
avista_digital_exchange_sdk/iotUtil.py
avista_digital_exchange_sdk/logger.py
avista_digital_exchange_sdk/subscriptionClient.py
avista_digital_exchange_sdk/async_graphql_client/__init__.py
avista_digital_exchange_sdk/async_graphql_client/base_model.py
avista_digital_exchange_sdk/async_graphql_client/client.py
avista_digital_exchange_sdk/async_graphql_client/data_capture_publish_data.py
avista_digital_exchange_sdk/async_graphql_client/data_capture_start_capture.py
avista_digital_exchange_sdk/async_graphql_client/data_capture_stop_capture.py
avista_digital_exchange_sdk/async_graphql_client/enums.py
avista_digital_exchange_sdk/async_graphql_client/exceptions.py
avista_digital_exchange_sdk/async_graphql_client/input_types.py
avista_digital_exchange_sdk/async_graphql_client/iot_publish.py
avista_digital_exchange_sdk/async_graphql_client/modified_async_base_client.py
avista_digital_exchange_sdk/async_graphql_client/on_capture_publish_data.py
avista_digital_exchange_sdk/async_graphql_client/on_iot_publish.py
avista_digital_exchange_sdk/async_graphql_client/scalars.py
avista_digital_exchange_sdk/data_types/__init__.py
avista_digital_exchange_sdk/data_types/collaborative.py
avista_digital_exchange_sdk/data_types/collaborative_member_organization.py
avista_digital_exchange_sdk/data_types/collaborative_member_user.py
avista_digital_exchange_sdk/data_types/data_store.py
avista_digital_exchange_sdk/data_types/data_store_directory.py
avista_digital_exchange_sdk/data_types/data_store_file.py
avista_digital_exchange_sdk/data_types/data_store_object.py
avista_digital_exchange_sdk-1.1.0.dist-info/LICENSE
avista_digital_exchange_sdk-1.1.0.dist-info/METADATA
avista_digital_exchange_sdk-1.1.0.dist-info/WHEEL
avista_digital_exchange_sdk-1.1.0.dist-info/top_level.txt
avista_digital_exchange_sdk-1.1.0.dist-info/RECORD
