Metadata-Version: 2.2
Name: avista_digital_exchange_sdk
Version: 1.1.0
Summary: SDK to programmatically access the Avista Digital Exchange
Author-email: Justin Whicker <jwhicker@urbanova.org>, Jon Thompson <jon.thompson@avistacorp.com>
License:                     GNU GENERAL PUBLIC LICENSE
Project-URL: Homepage, https://energy.collaboratives.io/
Project-URL: Bug Tracker, https://github.com/Avista-Digital-Innovation/avista-digital-exchange-sdk/issues
Classifier: Programming Language :: Python :: 3
Classifier: Operating System :: OS Independent
Classifier: Development Status :: 4 - Beta
Classifier: License :: OSI Approved :: GNU General Public License v3 (GPLv3)
Requires-Python: >=3.11.2
License-File: LICENSE
Requires-Dist: requests
Requires-Dist: pydantic==1.10.8
Requires-Dist: httpx
Requires-Dist: websockets
Requires-Dist: certifi
Requires-Dist: pip-system-certs
